AUTHORS.rst
CHANGELOG.rst
INSTALL.rst
LICENSE
MANIFEST.in
README.rst
VERSION
setup.py
ionyweb/Makefile
ionyweb/__init__.py
ionyweb/context_processors.py
ionyweb/decorators.py
ionyweb/forms.py
ionyweb/settings.py
ionyweb/urls.py
ionyweb/utils.py
ionyweb/widgets.py
ionyweb.egg-info/PKG-INFO
ionyweb.egg-info/SOURCES.txt
ionyweb.egg-info/dependency_links.txt
ionyweb.egg-info/entry_points.txt
ionyweb.egg-info/not-zip-safe
ionyweb.egg-info/requires.txt
ionyweb.egg-info/top_level.txt
ionyweb/administration/__init__.py
ionyweb/administration/models.py
ionyweb/administration/permissions.py
ionyweb/administration/urls.py
ionyweb/administration/utils.py
ionyweb/administration/actions/__init__.py
ionyweb/administration/actions/utils.py
ionyweb/administration/actions/views.py
ionyweb/administration/templatetags/__init__.py
ionyweb/administration/templatetags/actions_admin_tags.py
ionyweb/administration/templatetags/api_actions_admin_tags.py
ionyweb/administration/tests/__init__.py
ionyweb/administration/tests/actions.py
ionyweb/administration/tests/layouts.py
ionyweb/administration/tests/login.py
ionyweb/administration/tests/pages.py
ionyweb/administration/tests/plugins.py
ionyweb/administration/tests/utils.py
ionyweb/administration/tests/website.py
ionyweb/administration/views/__init__.py
ionyweb/administration/views/action.py
ionyweb/administration/views/apps.py
ionyweb/administration/views/design.py
ionyweb/administration/views/file_manager.py
ionyweb/administration/views/login.py
ionyweb/administration/views/manifest.py
ionyweb/administration/views/page.py
ionyweb/administration/views/plugin.py
ionyweb/administration/views/test.py
ionyweb/administration/views/users.py
ionyweb/administration/views/website.py
ionyweb/authentication/__init__.py
ionyweb/authentication/forms.py
ionyweb/authentication/models.py
ionyweb/authentication/tests.py
ionyweb/authentication/views.py
ionyweb/authentication/migrations/0001_initial.py
ionyweb/authentication/migrations/0002_auto__add_field_userprofile_file_manager_display_mode.py
ionyweb/authentication/migrations/__init__.py
ionyweb/bin/__init__.py
ionyweb/bin/manage.py
ionyweb/bin/quickstart.py
ionyweb/bin/templates/app_templates/admin.py.tpl
