Metadata-Version: 1.0
Name: ionyweb
Version: 0.3
Summary: A javascript UI based on REST API CMS based on Django.
Home-page: https://github.com/ionyse/ionyweb
Author: Ionyse
Author-email: contact@ionyse.com
License: BSD
Keywords: django cms
Platform: UNKNOWN
Classifier: Development Status :: 1 - Planning
Classifier: License :: OSI Approved :: BSD License
Classifier: Programming Language :: Python :: 2.7
Classifier: Framework :: Django
